odoo8_addon_procurement_mrp_no_confirm-8.0.1.0.0-py2.7-nspkg.pth
odoo_addons/procurement_mrp_no_confirm/__openerp__.py
odoo_addons/procurement_mrp_no_confirm/__init__.py
odoo_addons/procurement_mrp_no_confirm/README.rst
odoo_addons/procurement_mrp_no_confirm/models/mrp_production.py
odoo_addons/procurement_mrp_no_confirm/models/__init__.py
odoo_addons/procurement_mrp_no_confirm/models/procurement_order.py
odoo_addons/procurement_mrp_no_confirm/i18n/it.po
odoo_addons/procurement_mrp_no_confirm/i18n/es.po
odoo_addons/procurement_mrp_no_confirm/i18n/ro.po
odoo_addons/procurement_mrp_no_confirm/i18n/sl.po
odoo_addons/procurement_mrp_no_confirm/i18n/pt_BR.po
odoo_addons/procurement_mrp_no_confirm/data/mrp_production_workflow.xml
odoo_addons/procurement_mrp_no_confirm/tests/test_procurement.py
odoo_addons/procurement_mrp_no_confirm/tests/__init__.py
odoo_addons/procurement_mrp_no_confirm/static/description/icon.png
odoo8_addon_procurement_mrp_no_confirm-8.0.1.0.0.dist-info/top_level.txt
odoo8_addon_procurement_mrp_no_confirm-8.0.1.0.0.dist-info/WHEEL
odoo8_addon_procurement_mrp_no_confirm-8.0.1.0.0.dist-info/RECORD
odoo8_addon_procurement_mrp_no_confirm-8.0.1.0.0.dist-info/metadata.json
odoo8_addon_procurement_mrp_no_confirm-8.0.1.0.0.dist-info/DESCRIPTION.rst
odoo8_addon_procurement_mrp_no_confirm-8.0.1.0.0.dist-info/METADATA
odoo8_addon_procurement_mrp_no_confirm-8.0.1.0.0.dist-info/namespace_packages.txt
